byudml/__init__.py
byudml/imputer/__init__.py
byudml/imputer/random_sampling_imputer.py
byudml/metafeature_extraction/__init__.py
byudml/metafeature_extraction/metafeature_extraction.py
byudml/metafeature_extraction/metalearn_to_d3m_map.json
byudml/profiler/__init__.py
byudml/profiler/model.zip
byudml/profiler/profiler_primitive.py
byudml-0.7.7.dist-info/LICENSE
byudml-0.7.7.dist-info/METADATA
byudml-0.7.7.dist-info/WHEEL
byudml-0.7.7.dist-info/entry_points.txt
byudml-0.7.7.dist-info/top_level.txt
byudml-0.7.7.dist-info/RECORD
