Metadata-Version: 2.1
Name: byudml
Version: 0.7.7
Summary: A collection of DARPA D3M primitives developed by BYU
Home-page: https://gitlab.com/datadrivendiscovery/contrib/byu-d3m-primitives
Author: Roland Laboulaye, Brandom Schoenfeld, Jarom Christensen
Maintainer: Remi Rampin
Maintainer-email: remi.rampin@nyu.edu
License: MIT
Keywords: metalearning,metafeature,machine learning,metalearn,d3m_primitive
Platform: UNKNOWN
Requires-Dist: d3m
Requires-Dist: metalearn (==0.6.2)
Requires-Dist: numpy
Requires-Dist: pandas (==1.1.3)
Requires-Dist: sentence-transformers (<=0.3.0)
